lzham/__init__.py
lzham/_lzham.cp310-win_amd64.pyd
lzham/compress.py
lzham/decompress.py
pylzham-0.1.3.dist-info/LICENSE
pylzham-0.1.3.dist-info/METADATA
pylzham-0.1.3.dist-info/WHEEL
pylzham-0.1.3.dist-info/top_level.txt
pylzham-0.1.3.dist-info/RECORD
