Metadata-Version: 2.1
Name: pylzham
Version: 0.1.3
Summary: Python 3 Wrapper for LZHAM Codec
Home-page: https://github.com/Galaxy1036/pylzham
Author: GaLaXy1036
License: MIT
Platform: UNKNOWN
Classifier: Programming Language :: Python :: 3
Classifier: License :: OSI Approved :: MIT License
Classifier: Operating System :: OS Independent
License-File: LICENSE
